[
{
  "model": "accounts.customuser",
  "pk": 1,
  "fields": {
    "password": "pbkdf2_sha256$150000$XnTL38dcy4X9$ckhxiWdidicUHQT2O5dSJ9o7L7YnFisGoDcJGY1ZpNI=",
    "last_login": "2019-12-07T12:51:31.967Z",
    "is_superuser": true,
    "username": "myaldiz",
    "first_name": "",
    "last_name": "",
    "email": "berk17@gmail.com",
    "is_staff": true,
    "is_active": true,
    "date_joined": "2019-11-19T03:36:39.681Z",
    "groups": [],
    "user_permissions": []
  }
},
{
  "model": "accounts.customuser",
  "pk": 2,
  "fields": {
    "password": "pbkdf2_sha256$150000$U1KbVhMAA33E$bjZsoi61p4Zcu8VEgrKgS767ku2fECMIkJ0Axdq572s=",
    "last_login": "2019-11-19T04:33:23.826Z",
    "is_superuser": false,
    "username": "guest",
    "first_name": "",
    "last_name": "",
    "email": "guest@gmail.com",
    "is_staff": false,
    "is_active": true,
    "date_joined": "2019-11-19T04:33:13.410Z",
    "groups": [],
    "user_permissions": []
  }
},
{
  "model": "accounts.customuser",
  "pk": 3,
  "fields": {
    "password": "pbkdf2_sha256$150000$JQpa1KGNTS7T$JFI7hnfyFAPpfQM6rblssytLFHUQu7NUFptPbPgi7s8=",
    "last_login": "2019-12-07T13:35:37.410Z",
    "is_superuser": false,
    "username": "guest123",
    "first_name": "",
    "last_name": "",
    "email": "a@gmail.com",
    "is_staff": false,
    "is_active": true,
    "date_joined": "2019-12-07T12:51:25.909Z",
    "groups": [],
    "user_permissions": []
  }
},
{
  "model": "accounts.customuser",
  "pk": 4,
  "fields": {
    "password": "pbkdf2_sha256$150000$PGLTaS5MT0vW$BzJxxQ9PJQAIlAyAIiaDHKSvTICJm/FPzl55RRNBnw0=",
    "last_login": "2019-12-07T12:54:20.343Z",
    "is_superuser": false,
    "username": "Kewo",
    "first_name": "",
    "last_name": "",
    "email": "akjsnf@gmail.com",
    "is_staff": false,
    "is_active": true,
    "date_joined": "2019-12-07T12:54:15.937Z",
    "groups": [],
    "user_permissions": []
  }
},
{
  "model": "accounts.customuser",
  "pk": 5,
  "fields": {
    "password": "pbkdf2_sha256$150000$pDBk09qnZI8J$aueu7bbJ3wrcVp0VKV9nq/ePrbvi4CTn4d3+V4zlP8I=",
    "last_login": "2019-12-07T13:13:51.978Z",
    "is_superuser": true,
    "username": "waleed",
    "first_name": "",
    "last_name": "",
    "email": "w@gmail.com",
    "is_staff": true,
    "is_active": true,
    "date_joined": "2019-12-07T13:13:37.694Z",
    "groups": [],
    "user_permissions": []
  }
},
{
  "model": "accounts.customuser",
  "pk": 6,
  "fields": {
    "password": "pbkdf2_sha256$150000$1ibYcAGsjyan$E958IzFLwfVC5vdTiFt0qLOL+I/xHd+o0mH+0j/7YS4=",
    "last_login": "2019-12-07T13:21:13Z",
    "is_superuser": true,
    "username": "asem",
    "first_name": "",
    "last_name": "",
    "email": "mahmoudasem00@gmail.com",
    "is_staff": true,
    "is_active": true,
    "date_joined": "2019-12-07T13:21:08Z",
    "groups": [],
    "user_permissions": []
  }
},
{
  "model": "accounts.customuser",
  "pk": 7,
  "fields": {
    "password": "pbkdf2_sha256$150000$jykZLRocbonb$gY249nS61Bh2ils6vYsbXIdu5hsuw8XB7dj1BCn02YA=",
    "last_login": "2019-12-07T13:31:48.669Z",
    "is_superuser": false,
    "username": "asem00",
    "first_name": "",
    "last_name": "",
    "email": "mahmoudasem00@gmail.com",
    "is_staff": false,
    "is_active": true,
    "date_joined": "2019-12-07T13:31:40.013Z",
    "groups": [],
    "user_permissions": []
  }
},
{
  "model": "accounts.customuser",
  "pk": 8,
  "fields": {
    "password": "pbkdf2_sha256$150000$CyaHQWudNVqW$vw0xjPjq5vpdupTfc9H30w3pJu3x0skzObtnBLlxsSs=",
    "last_login": "2019-12-07T13:32:15.813Z",
    "is_superuser": false,
    "username": "waleed1",
    "first_name": "",
    "last_name": "",
    "email": "waleedanwar.bss@gmail.com",
    "is_staff": false,
    "is_active": true,
    "date_joined": "2019-12-07T13:32:00.574Z",
    "groups": [],
    "user_permissions": []
  }
},
{
  "model": "accounts.customuser",
  "pk": 9,
  "fields": {
    "password": "pbkdf2_sha256$150000$H51fKGAh4mKI$o3frs30HrQLUOkjYnMfTIaHfE1AXCbH01iNKNPDAx+0=",
    "last_login": "2019-12-07T13:35:08.674Z",
    "is_superuser": true,
    "username": "Timothy",
    "first_name": "",
    "last_name": "",
    "email": "me@email.com",
    "is_staff": true,
    "is_active": true,
    "date_joined": "2019-12-07T13:34:07Z",
    "groups": [],
    "user_permissions": []
  }
},
{
  "model": "accounts.customuser",
  "pk": 10,
  "fields": {
    "password": "pbkdf2_sha256$150000$p9JgL9WzQjFL$o6HJEL5ag0ZD28wCkJVR8VerXEOsylpd63gdjOvGors=",
    "last_login": "2019-12-07T13:35:17.134Z",
    "is_superuser": true,
    "username": "Timothy2",
    "first_name": "",
    "last_name": "",
    "email": "me1@email.com",
    "is_staff": true,
    "is_active": true,
    "date_joined": "2019-12-07T13:34:24Z",
    "groups": [],
    "user_permissions": []
  }
}
]
